quintagroup.xmlsec.init-0.2.0-py3.7-nspkg.pth
quintagroup/xmlsec/init/__init__.py
quintagroup.xmlsec.init-0.2.0.dist-info/LICENSE
quintagroup.xmlsec.init-0.2.0.dist-info/METADATA
quintagroup.xmlsec.init-0.2.0.dist-info/WHEEL
quintagroup.xmlsec.init-0.2.0.dist-info/entry_points.txt
quintagroup.xmlsec.init-0.2.0.dist-info/namespace_packages.txt
quintagroup.xmlsec.init-0.2.0.dist-info/top_level.txt
quintagroup.xmlsec.init-0.2.0.dist-info/RECORD
